setup.py
skny_dsnd_prob/Binomialdistribution.py
skny_dsnd_prob/Gaussiandistribution.py
skny_dsnd_prob/Generaldistribution.py
skny_dsnd_prob/__init__.py
skny_dsnd_prob.egg-info/PKG-INFO
skny_dsnd_prob.egg-info/SOURCES.txt
skny_dsnd_prob.egg-info/dependency_links.txt
skny_dsnd_prob.egg-info/not-zip-safe
skny_dsnd_prob.egg-info/top_level.txt